pylfs/__init__.py
pylfs/pylfs.py
pylfs-0.0.0.dist-info/LICENSE
pylfs-0.0.0.dist-info/METADATA
pylfs-0.0.0.dist-info/WHEEL
pylfs-0.0.0.dist-info/entry_points.txt
pylfs-0.0.0.dist-info/top_level.txt
pylfs-0.0.0.dist-info/RECORD
